{"mean":{"confidence_interval":{"confidence_level":0.95,"lower_bound":99965617.26935118,"upper_bound":100093120.0178611},"point_estimate":100026062.05825396,"standard_error":32756.589401691846},"median":{"confidence_interval":{"confidence_level":0.95,"lower_bound":99916225.25,"upper_bound":100098063.7},"point_estimate":100018622.55555555,"standard_error":49243.54473654878},"median_abs_dev":{"confidence_interval":{"confidence_level":0.95,"lower_bound":10240.379793193235,"upper_bound":211414.45670663426},"point_estimate":118123.62424622691,"standard_error":46184.40076960794},"slope":{"confidence_interval":{"confidence_level":0.95,"lower_bound":99947640.9,"upper_bound":100072263.16990955},"point_estimate":100017134.73246753,"standard_error":32015.78644177379},"std_dev":{"confidence_interval":{"confidence_level":0.95,"lower_bound":60218.87552140422,"upper_bound":142431.88148577078},"point_estimate":109140.23150085009,"standard_error":22893.339960623995}}