{"mean":{"confidence_interval":{"confidence_level":0.95,"lower_bound":831984.5588506625,"upper_bound":841981.0508409785},"point_estimate":836748.6653873599,"standard_error":2564.6597219128435},"median":{"confidence_interval":{"confidence_level":0.95,"lower_bound":829185.1804281345,"upper_bound":843764.3821100917},"point_estimate":836127.2319062182,"standard_error":3094.932481318916},"median_abs_dev":{"confidence_interval":{"confidence_level":0.95,"lower_bound":1960.3213422615654,"upper_bound":15778.839536199765},"point_estimate":7786.875763590233,"standard_error":3778.84413138877},"slope":{"confidence_interval":{"confidence_level":0.95,"lower_bound":835173.8151509108,"upper_bound":842139.9366161488},"point_estimate":837914.1410699392,"standard_error":1768.31369157986},"std_dev":{"confidence_interval":{"confidence_level":0.95,"lower_bound":4239.335027304135,"upper_bound":10732.594765334985},"point_estimate":8567.757389648374,"standard_error":1672.5004207241666}}