{"mean":{"confidence_interval":{"confidence_level":0.95,"lower_bound":79154196.02475,"upper_bound":80623890.09449999},"point_estimate":79861396.14,"standard_error":375492.8798153375},"median":{"confidence_interval":{"confidence_level":0.95,"lower_bound":78829669.0,"upper_bound":80497337.0},"point_estimate":79606178.5,"standard_error":427833.6860285521},"median_abs_dev":{"confidence_interval":{"confidence_level":0.95,"lower_bound":2645773.5050406307,"upper_bound":4126814.8028343916},"point_estimate":3422704.353734851,"standard_error":391693.7126664612},"slope":null,"std_dev":{"confidence_interval":{"confidence_level":0.95,"lower_bound":2814044.625023853,"upper_bound":4902776.82483085},"point_estimate":3774148.2108287727,"standard_error":564576.0486094365}}