{"mean":{"confidence_interval":{"confidence_level":0.95,"lower_bound":1228519.2561507935,"upper_bound":1280482.3051785713},"point_estimate":1253322.1855753968,"standard_error":13342.021885236529},"median":{"confidence_interval":{"confidence_level":0.95,"lower_bound":1228912.482638889,"upper_bound":1277792.5},"point_estimate":1247811.875,"standard_error":10784.301545548173},"median_abs_dev":{"confidence_interval":{"confidence_level":0.95,"lower_bound":8071.830231696367,"upper_bound":72754.88720834255},"point_estimate":21935.702010563367,"standard_error":16688.4239434461},"slope":{"confidence_interval":{"confidence_level":0.95,"lower_bound":1220844.92046956,"upper_bound":1309376.0165929203},"point_estimate":1263206.1376623376,"standard_error":24376.023117978664},"std_dev":{"confidence_interval":{"confidence_level":0.95,"lower_bound":16155.122250522534,"upper_bound":60967.21182445145},"point_estimate":44412.59694962314,"standard_error":11363.17494190748}}