{"mean":{"confidence_interval":{"confidence_level":0.95,"lower_bound":18927936.56799057,"upper_bound":19053256.053995535},"point_estimate":18985758.11676588,"standard_error":32178.767770695664},"median":{"confidence_interval":{"confidence_level":0.95,"lower_bound":18911694.65,"upper_bound":19027327.285714287},"point_estimate":18975999.645833336,"standard_error":28734.049411258813},"median_abs_dev":{"confidence_interval":{"confidence_level":0.95,"lower_bound":18676.280980928812,"upper_bound":154506.88602570444},"point_estimate":82361.75997528397,"standard_error":33883.18641712442},"slope":{"confidence_interval":{"confidence_level":0.95,"lower_bound":18886882.42991914,"upper_bound":18988216.340876836},"point_estimate":18928556.40909091,"standard_error":25086.062861920993},"std_dev":{"confidence_interval":{"confidence_level":0.95,"lower_bound":39937.8762117739,"upper_bound":151362.33047796288},"point_estimate":106961.52741615036,"standard_error":30897.196969506753}}