{"mean":{"confidence_interval":{"confidence_level":0.95,"lower_bound":10637368.004466599,"upper_bound":10795719.717420634},"point_estimate":10730291.346741622,"standard_error":41822.26025443788},"median":{"confidence_interval":{"confidence_level":0.95,"lower_bound":10709140.050925925,"upper_bound":10826955.6},"point_estimate":10753708.006944444,"standard_error":31047.828048519405},"median_abs_dev":{"confidence_interval":{"confidence_level":0.95,"lower_bound":9902.852377521893,"upper_bound":136537.58387180697},"point_estimate":85452.34081375078,"standard_error":33204.142158577655},"slope":{"confidence_interval":{"confidence_level":0.95,"lower_bound":10728341.1640893,"upper_bound":10798130.920894584},"point_estimate":10765733.589033188,"standard_error":17958.26546806599},"std_dev":{"confidence_interval":{"confidence_level":0.95,"lower_bound":39163.88010021198,"upper_bound":207556.9220298535},"point_estimate":139198.6951978091,"standard_error":54051.8013116784}}