{"mean":{"confidence_interval":{"confidence_level":0.95,"lower_bound":66103195.33499999,"upper_bound":66302491.3225},"point_estimate":66192114.0,"standard_error":51225.883164545674},"median":{"confidence_interval":{"confidence_level":0.95,"lower_bound":66091152.0,"upper_bound":66318393.0},"point_estimate":66110317.666666664,"standard_error":60144.23827688894},"median_abs_dev":{"confidence_interval":{"confidence_level":0.95,"lower_bound":8728.560245035238,"upper_bound":278692.9655522145},"point_estimate":68138.07089030743,"standard_error":70048.40363016928},"slope":null,"std_dev":{"confidence_interval":{"confidence_level":0.95,"lower_bound":53340.92811999286,"upper_bound":231806.90006973146},"point_estimate":170015.70109148632,"standard_error":46775.96346265268}}