{"mean":{"confidence_interval":{"confidence_level":0.95,"lower_bound":19829231.822406247,"upper_bound":19961370.792889882},"point_estimate":19896712.948154762,"standard_error":33929.21614532781},"median":{"confidence_interval":{"confidence_level":0.95,"lower_bound":19803645.9,"upper_bound":19983770.6875},"point_estimate":19904305.601190478,"standard_error":45627.28568086376},"median_abs_dev":{"confidence_interval":{"confidence_level":0.95,"lower_bound":35226.76069959998,"upper_bound":188114.89774279186},"point_estimate":126857.38182783329,"standard_error":40222.501645421165},"slope":{"confidence_interval":{"confidence_level":0.95,"lower_bound":19780766.89728021,"upper_bound":19942041.447439354},"point_estimate":19855706.602597404,"standard_error":41075.18855806877},"std_dev":{"confidence_interval":{"confidence_level":0.95,"lower_bound":63086.783033429485,"upper_bound":142611.95355066063},"point_estimate":112841.76684134557,"standard_error":20383.503615629343}}