{"mean":{"confidence_interval":{"confidence_level":0.95,"lower_bound":61206720.34275,"upper_bound":61411393.13725},"point_estimate":61308690.41,"standard_error":52101.52098748884},"median":{"confidence_interval":{"confidence_level":0.95,"lower_bound":61172791.0,"upper_bound":61433241.0},"point_estimate":61323862.0,"standard_error":74667.62425197482},"median_abs_dev":{"confidence_interval":{"confidence_level":0.95,"lower_bound":429721.9654709101,"upper_bound":698087.3867064714},"point_estimate":557952.0371943712,"standard_error":68561.07822123874},"slope":null,"std_dev":{"confidence_interval":{"confidence_level":0.95,"lower_bound":446394.80086596555,"upper_bound":599326.0263531981},"point_estimate":522403.81097762036,"standard_error":39300.77085984241}}