{"mean":{"confidence_interval":{"confidence_level":0.95,"lower_bound":216368645.89166668,"upper_bound":219789669.25000006},"point_estimate":218137429.96666664,"standard_error":878229.8853733062},"median":{"confidence_interval":{"confidence_level":0.95,"lower_bound":215512888.66666666,"upper_bound":220842405.66666666},"point_estimate":218632812.83333334,"standard_error":1203083.8706504474},"median_abs_dev":{"confidence_interval":{"confidence_level":0.95,"lower_bound":475159.4539642187,"upper_bound":4720947.962686434},"point_estimate":3589886.2803667635,"standard_error":1149378.303172501},"slope":null,"std_dev":{"confidence_interval":{"confidence_level":0.95,"lower_bound":1614522.0023809795,"upper_bound":3687286.027482688},"point_estimate":2925927.448333401,"standard_error":530383.7751558876}}